MANIFEST.in
README.rst
setup.cfg
setup.py
terra_submersa_cli.egg-info/PKG-INFO
terra_submersa_cli.egg-info/SOURCES.txt
terra_submersa_cli.egg-info/dependency_links.txt
terra_submersa_cli.egg-info/entry_points.txt
terra_submersa_cli.egg-info/requires.txt
terra_submersa_cli.egg-info/top_level.txt
tests/ts_cli/__init__.py
tests/ts_cli/test_output.py
tests/ts_cli/test_rest_cli.py
ts_cli/__init__.py
ts_cli/output.py
ts_cli/rest_cli.py
ts_cli/tiles/__init__.py
ts_cli/tiles/cli_tiles_exec.py