Metadata-Version: 1.1
Name: terra-submersa-cli
Version: 0.0.8
Summary: Command Line Interface to interact with Terra Submersa data
Home-page: https://gitlab.com/terra-submersa/terra-submersa-cli.git
Author: Alexandre Masselot
Author-email: terra-submersa-development@googlegroups.com
License: UNKNOWN
Keywords: cli REST client
Platform: UNKNOWN
Classifier: Development Status :: 3 - Alpha
Classifier: Intended Audience :: Science/Research
Classifier: Topic :: Scientific/Engineering :: GIS
Classifier: License :: OSI Approved :: MIT License
Classifier: Programming Language :: Python :: 3
Classifier: Programming Language :: Python :: 3.4
Classifier: Programming Language :: Python :: 3.5
Classifier: Programming Language :: Python :: 3.6
